tests/week4_counter.sv
`timescale 1ns/1ps

module week4_counter (
    input  logic       clk,
    input  logic       rst_n,
    input  logic       en,
    output logic [7:0] count
);

    always_ff @(posedge clk) begin
        if (!rst_n)
            count <= 8'd0;
        else if (en)
            count <= count + 8'd1;
    end

    initial begin
        $dumpfile("waveforms/week4_race.vcd");
        $dumpvars(0, week4_counter);
    end

endmodule

research/week4/waveforms/week4_race.vcd
$date
	Wed Sep 16 17:57:19 2026
$end
$version
	Icarus Verilog
$end
$timescale
	1ps
$end
$scope module week4_counter $end
$var wire 1 ! clk $end
$var wire 1 " en $end
$var wire 1 # rst_n $end
$var reg 8 $ count [7:0] $end
$upscope $end
$enddefinitions $end
#0
$dumpvars
b0 $
0#
0"
1!
$end
#5000
0!
#10000
1!
#15000
0!
#20000
1!
#25000
1#
0!
#30000
1!
#35000
1"
0!
#40000
b1 $
1!
#45000
0!
#50000
0"
b10 $
1!
#50001
0#
#55001
0!
#60001
b0 $
1!
#65001
0!
#70001
1!
#75001
0!
#80001
1!
#85001
1#
0!
#90001
1!
#95001
1"
0!
#100001
b1 $
1!
#105001
0"
0!
#110001
1!
#110002
0#
#115002
0!
#120002
b0 $
1!
#125002
0!
#130002
1!
#135002
0!
#140002
1!
#145002
1#
0!
#150002
1!
#155002
1"
0!
#160002
b1 $
1!
